Config_editor-0.9.2.dist-info/DESCRIPTION.rst
Config_editor-0.9.2.dist-info/METADATA
Config_editor-0.9.2.dist-info/RECORD
Config_editor-0.9.2.dist-info/WHEEL
Config_editor-0.9.2.dist-info/metadata.json
Config_editor-0.9.2.dist-info/top_level.txt
Config_editor-0.9.2.dist-info/zip-safe
config_editor/__init__.py
config_editor/_base_editor.py
config_editor/config_editor.py
config_editor/json_editor.py
config_editor/yaml_editor.py
