Metadata-Version: 2.0
Name: Config-editor
Version: 0.9.2
Summary: Context manager for changing content of config files
Home-page: https://github.com/penguinolog/Config-Editor
Author: Alexey Stepanov
Author-email: penguinolog@gmail.com
License: Apache License, Version 2.0
Keywords: config,ini,yaml,json
Platform: UNKNOWN
Classifier: Development Status :: 4 - Beta
Classifier: Intended Audience :: Developers
Classifier: Topic :: Software Development :: Libraries :: Python Modules
Classifier: License :: OSI Approved :: Apache Software License
Classifier: Programming Language :: Python :: 2
Classifier: Programming Language :: Python :: 2.7
Classifier: Programming Language :: Python :: 3
Classifier: Programming Language :: Python :: 3.3
Classifier: Programming Language :: Python :: 3.4
Classifier: Programming Language :: Python :: 3.5
Classifier: Programming Language :: Python :: 3.6
Classifier: Programming Language :: Python :: Implementation :: CPython
Classifier: Programming Language :: Python :: Implementation :: PyPy
Requires-Python: >=2.6,!=3.0.*,!=3.1.*,!=3.2.*
Requires-Dist: PyYAML (>=3)
Requires-Dist: six (>=1.10)
